{
  "status": "success",
  "data": {
    "resultType": "matrix",
    "result": [
      {
        "metric": {
          "DstK8S_Namespace": "default",
          "DstK8S_OwnerName": "kubernetes",
          "DstK8S_OwnerType": "Service",
          "SrcK8S_Namespace": "netobserv",
          "SrcK8S_OwnerName": "netobserv-controller-manager",
          "SrcK8S_OwnerType": "Deployment"
        },
        "values": [
          [
            1708009560,
            "1.0972222222222223"
          ],
          [
            1708009920,
            "2.4972222222222222"
          ],
          [
            1708010280,
            "2.826388888888889"
          ],
          [
            1708010640,
            "2.823611111111111"
          ],
          [
            1708011000,
            "2.8375"
          ],
          [
            1708011360,
            "3.0555555555555554"
          ],
          [
            1708011720,
            "3.0388888888888888"
          ]
        ]
      },
      {
        "metric": {
          "DstK8S_Namespace": "default",
          "DstK8S_OwnerName": "kubernetes",
          "DstK8S_OwnerType": "Service",
          "SrcK8S_Namespace": "openshift-console",
          "SrcK8S_OwnerName": "console",
          "SrcK8S_OwnerType": "Deployment"
        },
        "values": [
          [
            1708009560,
            "0.8402777777777778"
          ],
          [
            1708009920,
            "1.825"
          ],
          [
            1708010280,
            "4.169444444444444"
          ],
          [
            1708010640,
            "6.2972222222222225"
          ],
          [
            1708011000,
            "4.091666666666667"
          ],
          [
            1708011360,
            "7.348611111111111"
          ],
          [
            1708011720,
            "7.279166666666667"
          ]
        ]
      },
      {
        "metric": {
          "DstK8S_Namespace": "default",
          "DstK8S_OwnerName": "kubernetes",
          "DstK8S_OwnerType": "Service",
          "SrcK8S_Namespace": "openshift-console-operator",
          "SrcK8S_OwnerName": "console-operator",
          "SrcK8S_OwnerType": "Deployment"
        },
        "values": [
          [
            1708009560,
            "1.5791666666666666"
          ],
          [
            1708009920,
            "5.373611111111111"
          ],
          [
            1708010280,
            "6.926388888888889"
          ],
          [
            1708010640,
            "6.65"
          ],
          [
            1708011000,
            "6.708333333333333"
          ],
          [
            1708011360,
            "6.875"
          ],
          [
            1708011720,
            "7.529166666666667"
          ]
        ]
      },
      {
        "metric": {
          "DstK8S_Namespace": "default",
          "DstK8S_OwnerName": "kubernetes",
          "DstK8S_OwnerType": "Service",
          "SrcK8S_Namespace": "openshift-deployment-validation-operator",
          "SrcK8S_OwnerName": "deployment-validation-operator",
          "SrcK8S_OwnerType": "Deployment"
        },
        "values": [
          [
            1708009560,
            "4.519444444444445"
          ],
          [
            1708009920,
            "12.66388888888889"
          ],
          [
            1708010280,
            "16.290277777777778"
          ],
          [
            1708010640,
            "16.333333333333332"
          ],
          [
            1708011000,
            "16.42222222222222"
          ],
          [
            1708011360,
            "16.122222222222224"
          ],
          [
            1708011720,
            "16.108333333333334"
          ]
        ]
      },
      {
        "metric": {
          "DstK8S_Namespace": "default",
          "DstK8S_OwnerName": "kubernetes",
          "DstK8S_OwnerType": "Service",
          "SrcK8S_Namespace": "openshift-insights",
          "SrcK8S_OwnerName": "insights-operator",
          "SrcK8S_OwnerType": "Deployment"
        },
        "values": [
          [
            1708009920,
            "1.3486111111111112"
          ],
          [
            1708010280,
            "1.4097222222222223"
          ]
        ]
      },
      {
        "metric": {
          "DstK8S_Namespace": "default",
          "DstK8S_OwnerName": "kubernetes",
          "DstK8S_OwnerType": "Service",
          "SrcK8S_Namespace": "openshift-monitoring",
          "SrcK8S_OwnerName": "cluster-monitoring-operator",
          "SrcK8S_OwnerType": "Deployment"
        },
        "values": [
          [
            1708009560,
            "6.518055555555556"
          ],
          [
            1708009920,
            "6.736111111111111"
          ],
          [
            1708010640,
            "6.809722222222222"
          ],
          [
            1708011000,
            "6.798611111111111"
          ],
          [
            1708011360,
            "6.851388888888889"
          ],
          [
            1708011720,
            "6.844444444444444"
          ]
        ]
      },
      {
        "metric": {
          "DstK8S_Namespace": "default",
          "DstK8S_OwnerName": "kubernetes",
          "DstK8S_OwnerType": "Service",
          "SrcK8S_Namespace": "openshift-monitoring",
          "SrcK8S_OwnerName": "kube-state-metrics",
          "SrcK8S_OwnerType": "Deployment"
        },
        "values": [
          [
            1708009560,
            "1.261111111111111"
          ],
          [
            1708009920,
            "3.098611111111111"
          ],
          [
            1708010280,
            "3.745833333333333"
          ],
          [
            1708010640,
            "3.7777777777777777"
          ],
          [
            1708011000,
            "3.7555555555555555"
          ],
          [
            1708011360,
            "3.863888888888889"
          ],
          [
            1708011720,
            "3.8847222222222224"
          ]
        ]
      },
      {
        "metric": {
          "DstK8S_Namespace": "default",
          "DstK8S_OwnerName": "kubernetes",
          "DstK8S_OwnerType": "Service",
          "SrcK8S_Namespace": "openshift-monitoring",
          "SrcK8S_OwnerName": "prometheus-k8s",
          "SrcK8S_OwnerType": "StatefulSet"
        },
        "values": [
          [
            1708009920,
            "1.4527777777777777"
          ],
          [
            1708010280,
            "2.4027777777777777"
          ],
          [
            1708010640,
            "2.3222222222222224"
          ],
          [
            1708011000,
            "2.245833333333333"
          ],
          [
            1708011360,
            "2.613888888888889"
          ],
          [
            1708011720,
            "2.8513888888888888"
          ]
        ]
      },
      {
        "metric": {
          "DstK8S_Namespace": "default",
          "DstK8S_OwnerName": "kubernetes",
          "DstK8S_OwnerType": "Service",
          "SrcK8S_Namespace": "openshift-route-monitor-operator",
          "SrcK8S_OwnerName": "route-monitor-operator-controller-manager",
          "SrcK8S_OwnerType": "Deployment"
        },
        "values": [
          [
            1708009560,
            "0.7041666666666667"
          ],
          [
            1708009920,
            "1.961111111111111"
          ],
          [
            1708010280,
            "2.5319444444444446"
          ],
          [
            1708010640,
            "2.533333333333333"
          ],
          [
            1708011000,
            "2.5194444444444444"
          ],
          [
            1708011360,
            "2.5125"
          ],
          [
            1708011720,
            "2.529166666666667"
          ]
        ]
      },
      {
        "metric": {
          "DstK8S_Namespace": "netobserv",
          "DstK8S_OwnerName": "flowlogs-pipeline",
          "DstK8S_OwnerType": "DaemonSet",
          "SrcK8S_Namespace": "netobserv",
          "SrcK8S_OwnerName": "loki",
          "SrcK8S_OwnerType": "Pod"
        },
        "values": [
          [
            1708009560,
            "1.0277777777777777"
          ],
          [
            1708009920,
            "2.7888888888888888"
          ],
          [
            1708010280,
            "3.6041666666666665"
          ],
          [
            1708010640,
            "3.6791666666666667"
          ],
          [
            1708011000,
            "3.602777777777778"
          ],
          [
            1708011360,
            "3.5791666666666666"
          ],
          [
            1708011720,
            "3.638888888888889"
          ]
        ]
      },
      {
        "metric": {
          "DstK8S_Namespace": "netobserv",
          "DstK8S_OwnerName": "loki",
          "DstK8S_OwnerType": "Pod",
          "SrcK8S_Namespace": "netobserv",
          "SrcK8S_OwnerName": "flowlogs-pipeline",
          "SrcK8S_OwnerType": "DaemonSet"
        },
        "values": [
          [
            1708009560,
            "0.8805555555555555"
          ],
          [
            1708009920,
            "2.3222222222222224"
          ],
          [
            1708010280,
            "2.925"
          ],
          [
            1708010640,
            "2.933333333333333"
          ],
          [
            1708011000,
            "2.8958333333333335"
          ],
          [
            1708011360,
            "2.9569444444444444"
          ],
          [
            1708011720,
            "2.9875"
          ]
        ]
      },
      {
        "metric": {
          "DstK8S_Namespace": "netobserv",
          "DstK8S_OwnerName": "loki",
          "DstK8S_OwnerType": "Service",
          "SrcK8S_Namespace": "netobserv",
          "SrcK8S_OwnerName": "flowlogs-pipeline",
          "SrcK8S_OwnerType": "DaemonSet"
        },
        "values": [
          [
            1708009560,
            "1.6666666666666667"
          ],
          [
            1708009920,
            "4.581944444444445"
          ],
          [
            1708010280,
            "5.847222222222222"
          ],
          [
            1708010640,
            "5.823611111111111"
          ],
          [
            1708011000,
            "5.783333333333333"
          ],
          [
            1708011360,
            "5.813888888888889"
          ],
          [
            1708011720,
            "5.891666666666667"
          ]
        ]
      },
      {
        "metric": {
          "DstK8S_Namespace": "openshift-console",
          "DstK8S_OwnerName": "console",
          "DstK8S_OwnerType": "Deployment",
          "SrcK8S_Namespace": "openshift-ingress",
          "SrcK8S_OwnerName": "router-default",
          "SrcK8S_OwnerType": "Deployment"
        },
        "values": [
          [
            1708009560,
            "1.1180555555555556"
          ],
          [
            1708009920,
            "3.401388888888889"
          ],
          [
            1708010280,
            "4.886111111111111"
          ],
          [
            1708010640,
            "5.177777777777778"
          ],
          [
            1708011000,
            "4.7444444444444445"
          ],
          [
            1708011360,
            "6.802777777777778"
          ],
          [
            1708011720,
            "7.161111111111111"
          ]
        ]
      },
      {
        "metric": {
          "DstK8S_Namespace": "openshift-dns",
          "DstK8S_OwnerName": "dns-default",
          "DstK8S_OwnerType": "Service",
          "SrcK8S_Namespace": "netobserv",
          "SrcK8S_OwnerName": "flowlogs-pipeline",
          "SrcK8S_OwnerType": "DaemonSet"
        },
        "values": [
          [
            1708009560,
            "0.6722222222222223"
          ],
          [
            1708009920,
            "1.8722222222222222"
          ],
          [
            1708010280,
            "2.4"
          ],
          [
            1708010640,
            "2.4"
          ],
          [
            1708011000,
            "2.4"
          ],
          [
            1708011360,
            "2.35"
          ],
          [
            1708011720,
            "2.35"
          ]
        ]
      },
      {
        "metric": {
          "DstK8S_Namespace": "openshift-dns",
          "DstK8S_OwnerName": "dns-default",
          "DstK8S_OwnerType": "Service",
          "SrcK8S_Namespace": "openshift-monitoring",
          "SrcK8S_OwnerName": "thanos-querier",
          "SrcK8S_OwnerType": "Deployment"
        },
        "values": [
          [
            1708009560,
            "0.7861111111111111"
          ],
          [
            1708009920,
            "2.1194444444444445"
          ],
          [
            1708010280,
            "2.6666666666666665"
          ],
          [
            1708010640,
            "2.6666666666666665"
          ],
          [
            1708011000,
            "2.6666666666666665"
          ],
          [
            1708011360,
            "2.6666666666666665"
          ],
          [
            1708011720,
            "2.6666666666666665"
          ]
        ]
      },
      {
        "metric": {
          "DstK8S_Namespace": "openshift-ingress",
          "DstK8S_OwnerName": "router-default",
          "DstK8S_OwnerType": "Deployment",
          "SrcK8S_Namespace": "openshift-console",
          "SrcK8S_OwnerName": "console",
          "SrcK8S_OwnerType": "Deployment"
        },
        "values": [
          [
            1708009560,
            "0.95"
          ],
          [
            1708009920,
            "2.7569444444444446"
          ],
          [
            1708010280,
            "4.009722222222222"
          ],
          [
            1708010640,
            "4.365277777777778"
          ],
          [
            1708011000,
            "3.890277777777778"
          ],
          [
            1708011360,
            "6.426388888888889"
          ],
          [
            1708011720,
            "6.697222222222222"
          ]
        ]
      },
      {
        "metric": {
          "DstK8S_Namespace": "openshift-ingress",
          "DstK8S_OwnerName": "router-default",
          "DstK8S_OwnerType": "Deployment",
          "SrcK8S_Namespace": "openshift-monitoring",
          "SrcK8S_OwnerName": "prometheus-k8s",
          "SrcK8S_OwnerType": "StatefulSet"
        },
        "values": [
          [
            1708009560,
            "0.7916666666666666"
          ],
          [
            1708009920,
            "2.158333333333333"
          ],
          [
            1708010280,
            "2.7333333333333334"
          ],
          [
            1708010640,
            "2.7333333333333334"
          ],
          [
            1708011000,
            "2.7319444444444443"
          ],
          [
            1708011360,
            "2.709722222222222"
          ],
          [
            1708011720,
            "2.7111111111111112"
          ]
        ]
      },
      {
        "metric": {
          "DstK8S_Namespace": "openshift-monitoring",
          "DstK8S_OwnerName": "alertmanager-main",
          "DstK8S_OwnerType": "StatefulSet",
          "SrcK8S_Namespace": "openshift-ingress",
          "SrcK8S_OwnerName": "router-default",
          "SrcK8S_OwnerType": "Deployment"
        },
        "values": [
          [
            1708009560,
            "0.4583333333333333"
          ],
          [
            1708009920,
            "1.2583333333333333"
          ],
          [
            1708010280,
            "1.6"
          ],
          [
            1708010640,
            "1.6"
          ],
          [
            1708011000,
            "1.6"
          ],
          [
            1708011360,
            "1.5888888888888888"
          ],
          [
            1708011720,
            "1.5888888888888888"
          ]
        ]
      },
      {
        "metric": {
          "DstK8S_Namespace": "openshift-monitoring",
          "DstK8S_OwnerName": "alertmanager-main",
          "DstK8S_OwnerType": "StatefulSet",
          "SrcK8S_Namespace": "openshift-monitoring",
          "SrcK8S_OwnerName": "alertmanager-main",
          "SrcK8S_OwnerType": "StatefulSet"
        },
        "values": [
          [
            1708009560,
            "0.7486111111111111"
          ],
          [
            1708009920,
            "2.061111111111111"
          ],
          [
            1708010280,
            "2.6222222222222222"
          ],
          [
            1708010640,
            "2.6305555555555555"
          ],
          [
            1708011000,
            "2.636111111111111"
          ],
          [
            1708011360,
            "2.598611111111111"
          ],
          [
            1708011720,
            "2.575"
          ]
        ]
      },
      {
        "metric": {
          "DstK8S_Namespace": "openshift-monitoring",
          "DstK8S_OwnerName": "kube-state-metrics",
          "DstK8S_OwnerType": "Deployment",
          "SrcK8S_Namespace": "openshift-monitoring",
          "SrcK8S_OwnerName": "prometheus-k8s",
          "SrcK8S_OwnerType": "StatefulSet"
        },
        "values": [
          [
            1708009560,
            "0.5666666666666667"
          ],
          [
            1708009920,
            "1.761111111111111"
          ],
          [
            1708010280,
            "2.3430555555555554"
          ],
          [
            1708010640,
            "2.352777777777778"
          ],
          [
            1708011000,
            "2.313888888888889"
          ],
          [
            1708011360,
            "2"
          ],
          [
            1708011720,
            "2.0708333333333333"
          ]
        ]
      },
      {
        "metric": {
          "DstK8S_Namespace": "openshift-monitoring",
          "DstK8S_OwnerName": "prometheus-k8s",
          "DstK8S_OwnerType": "StatefulSet",
          "SrcK8S_Namespace": "openshift-ingress",
          "SrcK8S_OwnerName": "router-default",
          "SrcK8S_OwnerType": "Deployment"
        },
        "values": [
          [
            1708009560,
            "0.9986111111111111"
          ],
          [
            1708009920,
            "2.7305555555555556"
          ],
          [
            1708010280,
            "3.463888888888889"
          ],
          [
            1708010640,
            "3.4652777777777777"
          ],
          [
            1708011000,
            "3.466666666666667"
          ],
          [
            1708011360,
            "3.4305555555555554"
          ],
          [
            1708011720,
            "3.4305555555555554"
          ]
        ]
      },
      {
        "metric": {
          "DstK8S_Namespace": "openshift-monitoring",
          "DstK8S_OwnerName": "prometheus-k8s",
          "DstK8S_OwnerType": "StatefulSet",
          "SrcK8S_Namespace": "openshift-monitoring",
          "SrcK8S_OwnerName": "kube-state-metrics",
          "SrcK8S_OwnerType": "Deployment"
        },
        "values": [
          [
            1708009560,
            "0.5722222222222222"
          ],
          [
            1708009920,
            "1.6916666666666667"
          ],
          [
            1708010280,
            "2.2583333333333333"
          ],
          [
            1708010640,
            "2.323611111111111"
          ],
          [
            1708011000,
            "2.2958333333333334"
          ],
          [
            1708011360,
            "2.0444444444444443"
          ],
          [
            1708011720,
            "2.0972222222222223"
          ]
        ]
      },
      {
        "metric": {
          "DstK8S_Namespace": "openshift-monitoring",
          "DstK8S_OwnerName": "prometheus-k8s",
          "DstK8S_OwnerType": "StatefulSet",
          "SrcK8S_Namespace": "openshift-monitoring",
          "SrcK8S_OwnerName": "prometheus-k8s",
          "SrcK8S_OwnerType": "StatefulSet"
        },
        "values": [
          [
            1708009560,
            "0.6722222222222223"
          ],
          [
            1708009920,
            "1.7777777777777777"
          ],
          [
            1708010280,
            "2.2055555555555557"
          ],
          [
            1708010640,
            "2.198611111111111"
          ],
          [
            1708011000,
            "2.191666666666667"
          ],
          [
            1708011360,
            "2.151388888888889"
          ],
          [
            1708011720,
            "2.154166666666667"
          ]
        ]
      },
      {
        "metric": {
          "DstK8S_Namespace": "openshift-monitoring",
          "DstK8S_OwnerName": "prometheus-k8s",
          "DstK8S_OwnerType": "StatefulSet",
          "SrcK8S_Namespace": "openshift-monitoring",
          "SrcK8S_OwnerName": "thanos-querier",
          "SrcK8S_OwnerType": "Deployment"
        },
        "values": [
          [
            1708009560,
            "1.1611111111111112"
          ],
          [
            1708009920,
            "3.1305555555555555"
          ],
          [
            1708010280,
            "3.9166666666666665"
          ],
          [
            1708010640,
            "3.9027777777777777"
          ],
          [
            1708011000,
            "3.915277777777778"
          ],
          [
            1708011360,
            "3.9291666666666667"
          ],
          [
            1708011720,
            "3.901388888888889"
          ]
        ]
      },
      {
        "metric": {
          "DstK8S_Namespace": "openshift-monitoring",
          "DstK8S_OwnerName": "thanos-querier",
          "DstK8S_OwnerType": "Deployment",
          "SrcK8S_Namespace": "openshift-ingress",
          "SrcK8S_OwnerName": "router-default",
          "SrcK8S_OwnerType": "Deployment"
        },
        "values": [
          [
            1708009560,
            "0.4652777777777778"
          ],
          [
            1708009920,
            "1.2652777777777777"
          ],
          [
            1708010280,
            "1.6"
          ],
          [
            1708010640,
            "1.6"
          ],
          [
            1708011000,
            "1.6"
          ],
          [
            1708011360,
            "1.5833333333333333"
          ],
          [
            1708011720,
            "1.5833333333333333"
          ]
        ]
      },
      {
        "metric": {
          "DstK8S_Namespace": "openshift-monitoring",
          "DstK8S_OwnerName": "thanos-querier",
          "DstK8S_OwnerType": "Deployment",
          "SrcK8S_Namespace": "openshift-monitoring",
          "SrcK8S_OwnerName": "prometheus-k8s",
          "SrcK8S_OwnerType": "StatefulSet"
        },
        "values": [
          [
            1708009560,
            "1.0652777777777778"
          ],
          [
            1708009920,
            "2.8694444444444445"
          ],
          [
            1708010280,
            "3.623611111111111"
          ],
          [
            1708010640,
            "3.6555555555555554"
          ],
          [
            1708011000,
            "3.6277777777777778"
          ],
          [
            1708011360,
            "3.6791666666666667"
          ],
          [
            1708011720,
            "3.6930555555555555"
          ]
        ]
      },
      {
        "metric": {
          "DstK8S_Namespace": "openshift-monitoring",
          "DstK8S_OwnerName": "thanos-querier",
          "DstK8S_OwnerType": "Deployment",
          "SrcK8S_Namespace": "openshift-user-workload-monitoring",
          "SrcK8S_OwnerName": "prometheus-user-workload",
          "SrcK8S_OwnerType": "StatefulSet"
        },
        "values": [
          [
            1708009560,
            "0.39861111111111114"
          ],
          [
            1708010280,
            "1.3"
          ],
          [
            1708010640,
            "1.2986111111111112"
          ],
          [
            1708011000,
            "1.2875"
          ],
          [
            1708011360,
            "1.2458333333333333"
          ],
          [
            1708011720,
            "1.3083333333333333"
          ]
        ]
      },
      {
        "metric": {
          "DstK8S_Namespace": "openshift-monitoring",
          "DstK8S_OwnerName": "thanos-querier",
          "DstK8S_OwnerType": "Deployment",
          "SrcK8S_Namespace": "openshift-user-workload-monitoring",
          "SrcK8S_OwnerName": "thanos-ruler-user-workload",
          "SrcK8S_OwnerType": "StatefulSet"
        },
        "values": [
          [
            1708009560,
            "0.44305555555555554"
          ],
          [
            1708009920,
            "1.1847222222222222"
          ],
          [
            1708010280,
            "1.4958333333333333"
          ],
          [
            1708010640,
            "1.5305555555555554"
          ],
          [
            1708011000,
            "1.5458333333333334"
          ],
          [
            1708011360,
            "1.5416666666666667"
          ],
          [
            1708011720,
            "1.5138888888888888"
          ]
        ]
      },
      {
        "metric": {
          "DstK8S_Namespace": "openshift-user-workload-monitoring",
          "DstK8S_OwnerName": "prometheus-user-workload",
          "DstK8S_OwnerType": "StatefulSet",
          "SrcK8S_Namespace": "openshift-ingress",
          "SrcK8S_OwnerName": "router-default",
          "SrcK8S_OwnerType": "Deployment"
        },
        "values": [
          [
            1708009560,
            "0.48194444444444445"
          ],
          [
            1708009920,
            "1.2930555555555556"
          ],
          [
            1708010280,
            "1.6222222222222222"
          ],
          [
            1708010640,
            "1.6222222222222222"
          ],
          [
            1708011000,
            "1.625"
          ],
          [
            1708011360,
            "1.6111111111111112"
          ],
          [
            1708011720,
            "1.601388888888889"
          ]
        ]
      },
      {
        "metric": {
          "DstK8S_Namespace": "openshift-user-workload-monitoring",
          "DstK8S_OwnerName": "prometheus-user-workload",
          "DstK8S_OwnerType": "StatefulSet",
          "SrcK8S_Namespace": "openshift-monitoring",
          "SrcK8S_OwnerName": "thanos-querier",
          "SrcK8S_OwnerType": "Deployment"
        },
        "values": [
          [
            1708009560,
            "0.6666666666666666"
          ],
          [
            1708009920,
            "1.8194444444444444"
          ],
          [
            1708010280,
            "2.286111111111111"
          ],
          [
            1708010640,
            "2.279166666666667"
          ],
          [
            1708011000,
            "2.275"
          ],
          [
            1708011360,
            "2.25"
          ],
          [
            1708011720,
            "2.2694444444444444"
          ]
        ]
      },
      {
        "metric": {
          "DstK8S_Namespace": "openshift-user-workload-monitoring",
          "DstK8S_OwnerName": "thanos-ruler-user-workload",
          "DstK8S_OwnerType": "StatefulSet",
          "SrcK8S_Namespace": "openshift-ingress",
          "SrcK8S_OwnerName": "router-default",
          "SrcK8S_OwnerType": "Deployment"
        },
        "values": [
          [
            1708009560,
            "0.46944444444444444"
          ],
          [
            1708009920,
            "1.2694444444444444"
          ],
          [
            1708010280,
            "1.6"
          ],
          [
            1708010640,
            "1.6"
          ],
          [
            1708011000,
            "1.5944444444444446"
          ],
          [
            1708011360,
            "1.5722222222222222"
          ],
          [
            1708011720,
            "1.5777777777777777"
          ]
        ]
      },
      {
        "metric": {
          "DstK8S_Namespace": "openshift-user-workload-monitoring",
          "DstK8S_OwnerName": "thanos-ruler-user-workload",
          "DstK8S_OwnerType": "StatefulSet",
          "SrcK8S_Namespace": "openshift-monitoring",
          "SrcK8S_OwnerName": "thanos-querier",
          "SrcK8S_OwnerType": "Deployment"
        },
        "values": [
          [
            1708009560,
            "0.6305555555555555"
          ],
          [
            1708009920,
            "1.6847222222222222"
          ],
          [
            1708010280,
            "2.126388888888889"
          ],
          [
            1708010640,
            "2.158333333333333"
          ],
          [
            1708011000,
            "2.1666666666666665"
          ],
          [
            1708011360,
            "2.1569444444444446"
          ],
          [
            1708011720,
            "2.1305555555555555"
          ]
        ]
      },
      {
        "metric": {
          "DstK8S_OwnerName": "ip-10-0-1-137.ec2.internal",
          "DstK8S_OwnerType": "Node",
          "SrcK8S_Namespace": "openshift-monitoring",
          "SrcK8S_OwnerName": "prometheus-k8s",
          "SrcK8S_OwnerType": "StatefulSet"
        },
        "values": [
          [
            1708009560,
            "2.5708333333333333"
          ],
          [
            1708009920,
            "6.972222222222222"
          ],
          [
            1708010280,
            "8.808333333333334"
          ],
          [
            1708010640,
            "8.793055555555556"
          ],
          [
            1708011000,
            "8.791666666666666"
          ],
          [
            1708011360,
            "8.795833333333333"
          ],
          [
            1708011720,
            "8.786111111111111"
          ]
        ]
      },
      {
        "metric": {
          "DstK8S_OwnerName": "ip-10-0-1-137.ec2.internal",
          "DstK8S_OwnerType": "Node",
          "SrcK8S_OwnerName": "ip-10-0-1-7.ec2.internal",
          "SrcK8S_OwnerType": "Node"
        },
        "values": [
          [
            1708009560,
            "16.558333333333334"
          ],
          [
            1708009920,
            "45.81388888888889"
          ],
          [
            1708010280,
            "58.670833333333334"
          ],
          [
            1708010640,
            "58.93194444444445"
          ],
          [
            1708011000,
            "58.525"
          ],
          [
            1708011360,
            "59.87361111111111"
          ],
          [
            1708011720,
            "60.53333333333333"
          ]
        ]
      },
      {
        "metric": {
          "DstK8S_OwnerName": "ip-10-0-1-7.ec2.internal",
          "DstK8S_OwnerType": "Node",
          "SrcK8S_Namespace": "netobserv",
          "SrcK8S_OwnerName": "netobserv-controller-manager",
          "SrcK8S_OwnerType": "Deployment"
        },
        "values": [
          [
            1708009560,
            "0.4013888888888889"
          ]
        ]
      },
      {
        "metric": {
          "DstK8S_OwnerName": "ip-10-0-1-7.ec2.internal",
          "DstK8S_OwnerType": "Node",
          "SrcK8S_Namespace": "openshift-monitoring",
          "SrcK8S_OwnerName": "prometheus-k8s",
          "SrcK8S_OwnerType": "StatefulSet"
        },
        "values": [
          [
            1708009560,
            "2.725"
          ],
          [
            1708009920,
            "7.35"
          ],
          [
            1708010280,
            "9.265277777777778"
          ],
          [
            1708010640,
            "9.280555555555555"
          ],
          [
            1708011000,
            "9.265277777777778"
          ],
          [
            1708011360,
            "9.213888888888889"
          ],
          [
            1708011720,
            "9.222222222222221"
          ]
        ]
      },
      {
        "metric": {
          "DstK8S_OwnerName": "ip-10-0-1-7.ec2.internal",
          "DstK8S_OwnerType": "Node",
          "SrcK8S_OwnerName": "ip-10-0-1-137.ec2.internal",
          "SrcK8S_OwnerType": "Node"
        },
        "values": [
          [
            1708009560,
            "17.21527777777778"
          ],
          [
            1708009920,
            "45.67777777777778"
          ],
          [
            1708010280,
            "57.30416666666667"
          ],
          [
            1708010640,
            "57.665277777777774"
          ],
          [
            1708011000,
            "57.168055555555554"
          ],
          [
            1708011360,
            "60.03333333333333"
          ],
          [
            1708011720,
            "60.547222222222224"
          ]
        ]
      },
      {
        "metric": {
          "SrcK8S_Namespace": "netobserv",
          "SrcK8S_OwnerName": "netobserv-controller-manager",
          "SrcK8S_OwnerType": "Deployment"
        },
        "values": [
          [
            1708009560,
            "1.0680555555555555"
          ],
          [
            1708009920,
            "2.4680555555555554"
          ],
          [
            1708010280,
            "2.826388888888889"
          ],
          [
            1708010640,
            "2.823611111111111"
          ],
          [
            1708011000,
            "2.8375"
          ],
          [
            1708011360,
            "3.0569444444444445"
          ],
          [
            1708011720,
            "3.040277777777778"
          ]
        ]
      },
      {
        "metric": {
          "SrcK8S_Namespace": "openshift-console",
          "SrcK8S_OwnerName": "console",
          "SrcK8S_OwnerType": "Deployment"
        },
        "values": [
          [
            1708009560,
            "0.95"
          ],
          [
            1708009920,
            "2.0861111111111112"
          ],
          [
            1708010280,
            "4.466666666666667"
          ],
          [
            1708010640,
            "6.586111111111111"
          ],
          [
            1708011000,
            "4.391666666666667"
          ],
          [
            1708011360,
            "7.698611111111111"
          ],
          [
            1708011720,
            "7.622222222222222"
          ]
        ]
      },
      {
        "metric": {
          "SrcK8S_Namespace": "openshift-console-operator",
          "SrcK8S_OwnerName": "console-operator",
          "SrcK8S_OwnerType": "Deployment"
        },
        "values": [
          [
            1708009560,
            "1.6861111111111111"
          ],
          [
            1708009920,
            "5.6930555555555555"
          ],
          [
            1708010280,
            "7.331944444444445"
          ],
          [
            1708010640,
            "7.048611111111111"
          ],
          [
            1708011000,
            "7.108333333333333"
          ],
          [
            1708011360,
            "7.277777777777778"
          ],
          [
            1708011720,
            "7.951388888888889"
          ]
        ]
      },
      {
        "metric": {
          "SrcK8S_Namespace": "openshift-deployment-validation-operator",
          "SrcK8S_OwnerName": "deployment-validation-operator",
          "SrcK8S_OwnerType": "Deployment"
        },
        "values": [
          [
            1708009560,
            "4.5055555555555555"
          ],
          [
            1708009920,
            "12.65"
          ],
          [
            1708010280,
            "16.290277777777778"
          ],
          [
            1708010640,
            "16.333333333333332"
          ],
          [
            1708011000,
            "16.42222222222222"
          ],
          [
            1708011360,
            "16.122222222222224"
          ],
          [
            1708011720,
            "16.108333333333334"
          ]
        ]
      },
      {
        "metric": {
          "SrcK8S_Namespace": "openshift-dns",
          "SrcK8S_OwnerName": "dns-default",
          "SrcK8S_OwnerType": "DaemonSet"
        },
        "values": [
          [
            1708009560,
            "0.4361111111111111"
          ],
          [
            1708010280,
            "1.4638888888888888"
          ],
          [
            1708010640,
            "1.4277777777777778"
          ],
          [
            1708011000,
            "1.4375"
          ],
          [
            1708011360,
            "1.45"
          ],
          [
            1708011720,
            "1.4097222222222223"
          ]
        ]
      },
      {
        "metric": {
          "SrcK8S_Namespace": "openshift-image-registry",
          "SrcK8S_OwnerName": "image-registry",
          "SrcK8S_OwnerType": "Deployment"
        },
        "values": [
          [
            1708009560,
            "1.1680555555555556"
          ],
          [
            1708009920,
            "3.272222222222222"
          ],
          [
            1708010280,
            "4.1819444444444445"
          ],
          [
            1708010640,
            "4.161111111111111"
          ],
          [
            1708011000,
            "4.126388888888889"
          ],
          [
            1708011360,
            "4.170833333333333"
          ],
          [
            1708011720,
            "4.261111111111111"
          ]
        ]
      },
      {
        "metric": {
          "SrcK8S_Namespace": "openshift-ingress",
          "SrcK8S_OwnerName": "router-default",
          "SrcK8S_OwnerType": "Deployment"
        },
        "values": [
          [
            1708009560,
            "2.040277777777778"
          ],
          [
            1708009920,
            "4.911111111111111"
          ],
          [
            1708010280,
            "7.051388888888889"
          ],
          [
            1708010640,
            "8.5625"
          ],
          [
            1708011000,
            "7.2027777777777775"
          ],
          [
            1708011360,
            "15.820833333333333"
          ],
          [
            1708011720,
            "15.915277777777778"
          ]
        ]
      },
      {
        "metric": {
          "SrcK8S_Namespace": "openshift-insights",
          "SrcK8S_OwnerName": "insights-operator",
          "SrcK8S_OwnerType": "Deployment"
        },
        "values": [
          [
            1708009920,
            "1.4541666666666666"
          ],
          [
            1708010280,
            "1.5152777777777777"
          ]
        ]
      },
      {
        "metric": {
          "SrcK8S_Namespace": "openshift-monitoring",
          "SrcK8S_OwnerName": "cluster-monitoring-operator",
          "SrcK8S_OwnerType": "Deployment"
        },
        "values": [
          [
            1708009560,
            "6.5152777777777775"
          ],
          [
            1708009920,
            "6.733333333333333"
          ],
          [
            1708010640,
            "6.809722222222222"
          ],
          [
            1708011000,
            "6.798611111111111"
          ],
          [
            1708011360,
            "6.851388888888889"
          ],
          [
            1708011720,
            "6.844444444444444"
          ]
        ]
      },
      {
        "metric": {
          "SrcK8S_Namespace": "openshift-monitoring",
          "SrcK8S_OwnerName": "kube-state-metrics",
          "SrcK8S_OwnerType": "Deployment"
        },
        "values": [
          [
            1708009560,
            "1.2416666666666667"
          ],
          [
            1708009920,
            "3.0791666666666666"
          ],
          [
            1708010280,
            "3.745833333333333"
          ],
          [
            1708010640,
            "3.7777777777777777"
          ],
          [
            1708011000,
            "3.7555555555555555"
          ],
          [
            1708011360,
            "3.863888888888889"
          ],
          [
            1708011720,
            "3.886111111111111"
          ]
        ]
      },
      {
        "metric": {
          "SrcK8S_Namespace": "openshift-monitoring",
          "SrcK8S_OwnerName": "prometheus-k8s",
          "SrcK8S_OwnerType": "StatefulSet"
        },
        "values": [
          [
            1708009560,
            "3.063888888888889"
          ],
          [
            1708009920,
            "9.051388888888889"
          ],
          [
            1708010280,
            "11.955555555555556"
          ],
          [
            1708010640,
            "11.877777777777778"
          ],
          [
            1708011000,
            "11.816666666666666"
          ],
          [
            1708011360,
            "12.1875"
          ],
          [
            1708011720,
            "12.431944444444444"
          ]
        ]
      },
      {
        "metric": {
          "SrcK8S_Namespace": "openshift-route-monitor-operator",
          "SrcK8S_OwnerName": "blackbox-exporter",
          "SrcK8S_OwnerType": "Deployment"
        },
        "values": [
          [
            1708009560,
            "0.4583333333333333"
          ],
          [
            1708009920,
            "1.2458333333333333"
          ],
          [
            1708010280,
            "1.575"
          ],
          [
            1708010640,
            "1.5791666666666666"
          ],
          [
            1708011000,
            "1.5888888888888888"
          ],
          [
            1708011360,
            "1.601388888888889"
          ],
          [
            1708011720,
            "1.5944444444444446"
          ]
        ]
      },
      {
        "metric": {
          "SrcK8S_Namespace": "openshift-route-monitor-operator",
          "SrcK8S_OwnerName": "route-monitor-operator-controller-manager",
          "SrcK8S_OwnerType": "Deployment"
        },
        "values": [
          [
            1708009560,
            "0.6972222222222222"
          ],
          [
            1708009920,
            "1.9555555555555555"
          ],
          [
            1708010280,
            "2.5347222222222223"
          ],
          [
            1708010640,
            "2.5347222222222223"
          ],
          [
            1708011000,
            "2.5208333333333335"
          ],
          [
            1708011360,
            "2.515277777777778"
          ],
          [
            1708011720,
            "2.5305555555555554"
          ]
        ]
      },
      {
        "metric": {
          "SrcK8S_OwnerName": "ip-10-0-1-137.ec2.internal",
          "SrcK8S_OwnerType": "Node"
        },
        "values": [
          [
            1708009560,
            "12.91388888888889"
          ],
          [
            1708009920,
            "30.997222222222224"
          ],
          [
            1708010280,
            "38.78472222222222"
          ],
          [
            1708010640,
            "41.68055555555556"
          ],
          [
            1708011000,
            "38.80416666666667"
          ],
          [
            1708011360,
            "47.01111111111111"
          ],
          [
            1708011720,
            "47.97222222222222"
          ]
        ]
      },
      {
        "metric": {
          "SrcK8S_OwnerName": "ip-10-0-1-7.ec2.internal",
          "SrcK8S_OwnerType": "Node"
        },
        "values": [
          [
            1708009560,
            "22.755555555555556"
          ],
          [
            1708009920,
            "54.102777777777774"
          ],
          [
            1708010280,
            "61.2"
          ],
          [
            1708010640,
            "66.49027777777778"
          ],
          [
            1708011000,
            "65.89444444444445"
          ],
          [
            1708011360,
            "72.83888888888889"
          ],
          [
            1708011720,
            "74.14166666666667"
          ]
        ]
      },
      {
        "metric": {},
        "values": [
          [
            1708009560,
            "0.6319444444444444"
          ],
          [
            1708009920,
            "1.7416666666666667"
          ],
          [
            1708010280,
            "2.2333333333333334"
          ],
          [
            1708010640,
            "2.2"
          ],
          [
            1708011000,
            "2.2222222222222223"
          ],
          [
            1708011360,
            "2.261111111111111"
          ],
          [
            1708011720,
            "2.2222222222222223"
          ]
        ]
      },
      {
        "metric": {
          "DstK8S_Namespace": "production",
          "DstK8S_OwnerName": "gateway-api",
          "DstK8S_OwnerType": "Gateway",
          "SrcK8S_Namespace": "production",
          "SrcK8S_OwnerName": "web-deployment",
          "SrcK8S_OwnerType": "Deployment"
        },
        "values": [
          [
            1708009560,
            "200.5"
          ],
          [
            1708009920,
            "225.8"
          ],
          [
            1708010280,
            "245.3"
          ],
          [
            1708010640,
            "258.7"
          ],
          [
            1708011000,
            "252.1"
          ],
          [
            1708011360,
            "265.4"
          ],
          [
            1708011720,
            "270.2"
          ]
        ]
      },
      {
        "metric": {
          "DstK8S_Namespace": "gateway-system",
          "DstK8S_OwnerName": "gateway-external",
          "DstK8S_OwnerType": "Gateway",
          "SrcK8S_Namespace": "gateway-system",
          "SrcK8S_OwnerName": "gateway-internal",
          "SrcK8S_OwnerType": "Gateway"
        },
        "values": [
          [
            1708009560,
            "150.2"
          ],
          [
            1708009920,
            "168.5"
          ],
          [
            1708010280,
            "182.3"
          ],
          [
            1708010640,
            "195.8"
          ],
          [
            1708011000,
            "188.1"
          ],
          [
            1708011360,
            "202.5"
          ],
          [
            1708011720,
            "210.7"
          ]
        ]
      },
      {
        "metric": {
          "DstK8S_Namespace": "vms",
          "DstK8S_OwnerName": "vm-ubuntu-server",
          "DstK8S_OwnerType": "VirtualMachine",
          "SrcK8S_Namespace": "vms",
          "SrcK8S_OwnerName": "vm-centos-server",
          "SrcK8S_OwnerType": "VirtualMachine"
        },
        "values": [
          [
            1708009560,
            "95.3"
          ],
          [
            1708009920,
            "108.7"
          ],
          [
            1708010280,
            "118.2"
          ],
          [
            1708010640,
            "125.8"
          ],
          [
            1708011000,
            "122.1"
          ],
          [
            1708011360,
            "132.5"
          ],
          [
            1708011720,
            "138.9"
          ]
        ]
      },
      {
        "metric": {
          "DstK8S_Namespace": "vms",
          "DstK8S_OwnerName": "vmi-windows",
          "DstK8S_OwnerType": "VirtualMachineInstance",
          "SrcK8S_Namespace": "vms",
          "SrcK8S_OwnerName": "vmi-linux",
          "SrcK8S_OwnerType": "VirtualMachineInstance"
        },
        "values": [
          [
            1708009560,
            "88.2"
          ],
          [
            1708009920,
            "98.5"
          ],
          [
            1708010280,
            "105.8"
          ],
          [
            1708010640,
            "112.3"
          ],
          [
            1708011000,
            "109.1"
          ],
          [
            1708011360,
            "118.7"
          ],
          [
            1708011720,
            "125.2"
          ]
        ]
      },
      {
        "metric": {
          "DstK8S_Namespace": "production",
          "DstK8S_OwnerName": "app-deployment",
          "DstK8S_OwnerType": "Deployment",
          "SrcK8S_Namespace": "vms",
          "SrcK8S_OwnerName": "vm-ubuntu-server",
          "SrcK8S_OwnerType": "VirtualMachine"
        },
        "values": [
          [
            1708009560,
            "65.4"
          ],
          [
            1708009920,
            "72.8"
          ],
          [
            1708010280,
            "78.1"
          ],
          [
            1708010640,
            "82.5"
          ],
          [
            1708011000,
            "79.9"
          ],
          [
            1708011360,
            "85.2"
          ],
          [
            1708011720,
            "88.7"
          ]
        ]
      }
    ],
    "stats": {
      "summary": {
        "bytesProcessedPerSecond": 271431036,
        "linesProcessedPerSecond": 413077,
        "totalBytesProcessed": 211370848,
        "totalLinesProcessed": 321675,
        "execTime": 0.77872763,
        "queueTime": 13.016442995,
        "subqueries": 0,
        "totalEntriesReturned": 58,
        "splits": 6,
        "shards": 48,
        "totalPostFilterLines": 199944,
        "totalStructuredMetadataBytesProcessed": 0
      },
      "querier": {
        "store": {
          "totalChunksRef": 0,
          "totalChunksDownloaded": 0,
          "chunksDownloadTime": 0,
          "chunk": {
            "headChunkBytes": 0,
            "headChunkLines": 0,
            "decompressedBytes": 0,
            "decompressedLines": 0,
            "compressedBytes": 0,
            "totalDuplicates": 0,
            "postFilterLines": 0,
            "headChunkStructuredMetadataBytes": 0,
            "decompressedStructuredMetadataBytes": 0
          }
        }
      },
      "ingester": {
        "totalReached": 48,
        "totalChunksMatched": 375,
        "totalBatches": 394,
        "totalLinesSent": 168379,
        "store": {
          "totalChunksRef": 16,
          "totalChunksDownloaded": 16,
          "chunksDownloadTime": 31495351,
          "chunk": {
            "headChunkBytes": 18864260,
            "headChunkLines": 28785,
            "decompressedBytes": 192506588,
            "decompressedLines": 292890,
            "compressedBytes": 43190086,
            "totalDuplicates": 0,
            "postFilterLines": 199944,
            "headChunkStructuredMetadataBytes": 0,
            "decompressedStructuredMetadataBytes": 0
          }
        }
      },
      "cache": {
        "chunk": {
          "entriesFound": 0,
          "entriesRequested": 0,
          "entriesStored": 0,
          "bytesReceived": 0,
          "bytesSent": 0,
          "requests": 0,
          "downloadTime": 0
        },
        "index": {
          "entriesFound": 0,
          "entriesRequested": 0,
          "entriesStored": 0,
          "bytesReceived": 0,
          "bytesSent": 0,
          "requests": 0,
          "downloadTime": 0
        },
        "result": {
          "entriesFound": 4,
          "entriesRequested": 6,
          "entriesStored": 3,
          "bytesReceived": 32903,
          "bytesSent": 0,
          "requests": 9,
          "downloadTime": 64186
        },
        "statsResult": {
          "entriesFound": 0,
          "entriesRequested": 0,
          "entriesStored": 0,
          "bytesReceived": 0,
          "bytesSent": 0,
          "requests": 0,
          "downloadTime": 0
        }
      }
    }
  }
}
