{
  "status": "success",
  "data": {
    "resultType": "matrix",
    "result": [
      {
        "metric": {
          "UdnId": "my-udn"
        },
        "values": [
          [
            1708011360,
            "0.041666666666666664"
          ],
          [
            1708011720,
            "0.6236111111111111"
          ]
        ]
      },
      {
        "metric": {
          "UdnId": "my-udn-2"
        },
        "values": [
          [
            1708011360,
            "0.036111111111111115"
          ],
          [
            1708011720,
            "0.49166666666666664"
          ]
        ]
      },
      {
        "metric": {
          "DstK8S_NetworkName": "production-network",
          "DstK8S_Type": "UserDefinedNetwork",
          "SrcAddr": "10.128.0.90",
          "SrcK8S_Name": "app-pod-1",
          "SrcK8S_Namespace": "production",
          "SrcK8S_OwnerName": "app-deployment",
          "SrcK8S_OwnerType": "Deployment",
          "SrcK8S_Type": "Pod"
        },
        "values": [
          [
            1708011360,
            "0.15"
          ],
          [
            1708011720,
            "0.25"
          ]
        ]
      },
      {
        "metric": {
          "DstK8S_NetworkName": "development-network",
          "DstK8S_Type": "UserDefinedNetwork",
          "SrcK8S_NetworkName": "production-network",
          "SrcK8S_Type": "UserDefinedNetwork"
        },
        "values": [
          [
            1708011360,
            "0.08"
          ],
          [
            1708011720,
            "0.12"
          ]
        ]
      },
      {
        "metric": {
          "DstK8S_NetworkName": "cluster-network",
          "DstK8S_Type": "ClusterUserDefinedNetwork",
          "SrcAddr": "10.128.0.100",
          "SrcK8S_Name": "cluster-pod",
          "SrcK8S_Namespace": "kube-system",
          "SrcK8S_OwnerName": "cluster-deployment",
          "SrcK8S_OwnerType": "Deployment",
          "SrcK8S_Type": "Pod"
        },
        "values": [
          [
            1708011360,
            "0.1"
          ],
          [
            1708011720,
            "0.18"
          ]
        ]
      }
    ],
    "stats": {
      "summary": {
        "bytesProcessedPerSecond": 379050316,
        "linesProcessedPerSecond": 577163,
        "totalBytesProcessed": 221936446,
        "totalLinesProcessed": 337933,
        "execTime": 0.585506558,
        "queueTime": 5.295528995,
        "subqueries": 0,
        "totalEntriesReturned": 5,
        "splits": 6,
        "shards": 48,
        "totalPostFilterLines": 810,
        "totalStructuredMetadataBytesProcessed": 0
      },
      "querier": {
        "store": {
          "totalChunksRef": 0,
          "totalChunksDownloaded": 0,
          "chunksDownloadTime": 0,
          "chunk": {
            "headChunkBytes": 0,
            "headChunkLines": 0,
            "decompressedBytes": 0,
            "decompressedLines": 0,
            "compressedBytes": 0,
            "totalDuplicates": 0,
            "postFilterLines": 0,
            "headChunkStructuredMetadataBytes": 0,
            "decompressedStructuredMetadataBytes": 0
          }
        }
      },
      "ingester": {
        "totalReached": 48,
        "totalChunksMatched": 375,
        "totalBatches": 56,
        "totalLinesSent": 802,
        "store": {
          "totalChunksRef": 16,
          "totalChunksDownloaded": 16,
          "chunksDownloadTime": 7855086,
          "chunk": {
            "headChunkBytes": 18755808,
            "headChunkLines": 28594,
            "decompressedBytes": 203180638,
            "decompressedLines": 309339,
            "compressedBytes": 43253118,
            "totalDuplicates": 0,
            "postFilterLines": 810,
            "headChunkStructuredMetadataBytes": 0,
            "decompressedStructuredMetadataBytes": 0
          }
        }
      },
      "cache": {
        "chunk": {
          "entriesFound": 0,
          "entriesRequested": 0,
          "entriesStored": 0,
          "bytesReceived": 0,
          "bytesSent": 0,
          "requests": 0,
          "downloadTime": 0
        },
        "index": {
          "entriesFound": 0,
          "entriesRequested": 0,
          "entriesStored": 0,
          "bytesReceived": 0,
          "bytesSent": 0,
          "requests": 0,
          "downloadTime": 0
        },
        "result": {
          "entriesFound": 4,
          "entriesRequested": 6,
          "entriesStored": 3,
          "bytesReceived": 1372,
          "bytesSent": 0,
          "requests": 9,
          "downloadTime": 63334
        },
        "statsResult": {
          "entriesFound": 0,
          "entriesRequested": 0,
          "entriesStored": 0,
          "bytesReceived": 0,
          "bytesSent": 0,
          "requests": 0,
          "downloadTime": 0
        }
      }
    }
  }
}
